{
    "GFS": [
        {
            "latest": "20260601_00",
            "previous": "20260531_18",
            "file": "GFS_shift_20260601_00_vs_20260531_18.gif"
        },
        {
            "latest": "20260601_00",
            "previous": "20260531_12",
            "file": "GFS_shift_20260601_00_vs_20260531_12.gif"
        },
        {
            "latest": "20260531_12",
            "previous": "20260531_06",
            "file": "GFS_shift_20260531_12_vs_20260531_06.gif"
        },
        {
            "latest": "20260531_12",
            "previous": "20260531_00",
            "file": "GFS_shift_20260531_12_vs_20260531_00.gif"
        },
        {
            "latest": "20260531_06",
            "previous": "20260531_00",
            "file": "GFS_shift_20260531_06_vs_20260531_00.gif"
        },
        {
            "latest": "20260531_06",
            "previous": "20260530_18",
            "file": "GFS_shift_20260531_06_vs_20260530_18.gif"
        },
        {
            "latest": "20260531_06",
            "previous": "20260530_12",
            "file": "GFS_shift_20260531_06_vs_20260530_12.gif"
        },
        {
            "latest": "20260531_00",
            "previous": "20260530_18",
            "file": "GFS_shift_20260531_00_vs_20260530_18.gif"
        },
        {
            "latest": "20260531_00",
            "previous": "20260530_12",
            "file": "GFS_shift_20260531_00_vs_20260530_12.gif"
        },
        {
            "latest": "20260531_00",
            "previous": "20260530_06",
            "file": "GFS_shift_20260531_00_vs_20260530_06.gif"
        },
        {
            "latest": "20260530_12",
            "previous": "20260530_06",
            "file": "GFS_shift_20260530_12_vs_20260530_06.gif"
        },
        {
            "latest": "20260530_12",
            "previous": "20260530_00",
            "file": "GFS_shift_20260530_12_vs_20260530_00.gif"
        }
    ],
    "GEFS": [
        {
            "latest": "20260601_00",
            "previous": "20260531_18",
            "file": "GEFS_shift_20260601_00_vs_20260531_18.gif"
        },
        {
            "latest": "20260531_12",
            "previous": "20260531_06",
            "file": "GEFS_shift_20260531_12_vs_20260531_06.gif"
        },
        {
            "latest": "20260531_06",
            "previous": "20260531_00",
            "file": "GEFS_shift_20260531_06_vs_20260531_00.gif"
        },
        {
            "latest": "20260531_00",
            "previous": "20260530_18",
            "file": "GEFS_shift_20260531_00_vs_20260530_18.gif"
        },
        {
            "latest": "20260530_12",
            "previous": "20260530_06",
            "file": "GEFS_shift_20260530_12_vs_20260530_06.gif"
        },
        {
            "latest": "20260530_06",
            "previous": "20260530_00",
            "file": "GEFS_shift_20260530_06_vs_20260530_00.gif"
        },
        {
            "latest": "20260530_00",
            "previous": "20260529_18",
            "file": "GEFS_shift_20260530_00_vs_20260529_18.gif"
        },
        {
            "latest": "20260529_12",
            "previous": "20260529_06",
            "file": "GEFS_shift_20260529_12_vs_20260529_06.gif"
        },
        {
            "latest": "20260529_06",
            "previous": "20260529_00",
            "file": "GEFS_shift_20260529_06_vs_20260529_00.gif"
        },
        {
            "latest": "20260529_00",
            "previous": "20260528_18",
            "file": "GEFS_shift_20260529_00_vs_20260528_18.gif"
        },
        {
            "latest": "20260528_12",
            "previous": "20260528_06",
            "file": "GEFS_shift_20260528_12_vs_20260528_06.gif"
        }
    ],
    "GEFS_35D": [
        {
            "latest": "20260321_00",
            "previous": "20260302_00",
            "file": "GEFS_35D_shift_20260321_00_vs_20260302_00.gif"
        },
        {
            "latest": "20260320_00",
            "previous": "20260302_00",
            "file": "GEFS_35D_shift_20260320_00_vs_20260302_00.gif"
        },
        {
            "latest": "20260319_00",
            "previous": "20260302_00",
            "file": "GEFS_35D_shift_20260319_00_vs_20260302_00.gif"
        },
        {
            "latest": "20260319_00",
            "previous": "20260228_00",
            "file": "GEFS_35D_shift_20260319_00_vs_20260228_00.gif"
        },
        {
            "latest": "20260318_00",
            "previous": "20260302_00",
            "file": "GEFS_35D_shift_20260318_00_vs_20260302_00.gif"
        },
        {
            "latest": "20260318_00",
            "previous": "20260228_00",
            "file": "GEFS_35D_shift_20260318_00_vs_20260228_00.gif"
        },
        {
            "latest": "20260317_00",
            "previous": "20260302_00",
            "file": "GEFS_35D_shift_20260317_00_vs_20260302_00.gif"
        },
        {
            "latest": "20260317_00",
            "previous": "20260228_00",
            "file": "GEFS_35D_shift_20260317_00_vs_20260228_00.gif"
        },
        {
            "latest": "20260316_00",
            "previous": "20260302_00",
            "file": "GEFS_35D_shift_20260316_00_vs_20260302_00.gif"
        },
        {
            "latest": "20260316_00",
            "previous": "20260228_00",
            "file": "GEFS_35D_shift_20260316_00_vs_20260228_00.gif"
        }
    ],
    "ECMWF": [
        {
            "latest": "20260601_00",
            "previous": "20260531_12",
            "file": "ECMWF_shift_20260601_00_vs_20260531_12.gif"
        },
        {
            "latest": "20260601_00",
            "previous": "20260531_00",
            "file": "ECMWF_shift_20260601_00_vs_20260531_00.gif"
        },
        {
            "latest": "20260601_00",
            "previous": "20260530_12",
            "file": "ECMWF_shift_20260601_00_vs_20260530_12.gif"
        },
        {
            "latest": "20260531_12",
            "previous": "20260531_00",
            "file": "ECMWF_shift_20260531_12_vs_20260531_00.gif"
        },
        {
            "latest": "20260531_12",
            "previous": "20260530_12",
            "file": "ECMWF_shift_20260531_12_vs_20260530_12.gif"
        },
        {
            "latest": "20260531_12",
            "previous": "20260530_00",
            "file": "ECMWF_shift_20260531_12_vs_20260530_00.gif"
        },
        {
            "latest": "20260531_00",
            "previous": "20260530_12",
            "file": "ECMWF_shift_20260531_00_vs_20260530_12.gif"
        },
        {
            "latest": "20260531_00",
            "previous": "20260530_00",
            "file": "ECMWF_shift_20260531_00_vs_20260530_00.gif"
        },
        {
            "latest": "20260531_00",
            "previous": "20260529_12",
            "file": "ECMWF_shift_20260531_00_vs_20260529_12.gif"
        },
        {
            "latest": "20260530_12",
            "previous": "20260530_00",
            "file": "ECMWF_shift_20260530_12_vs_20260530_00.gif"
        },
        {
            "latest": "20260530_12",
            "previous": "20260529_12",
            "file": "ECMWF_shift_20260530_12_vs_20260529_12.gif"
        },
        {
            "latest": "20260530_12",
            "previous": "20260529_00",
            "file": "ECMWF_shift_20260530_12_vs_20260529_00.gif"
        },
        {
            "latest": "20260530_00",
            "previous": "20260529_12",
            "file": "ECMWF_shift_20260530_00_vs_20260529_12.gif"
        }
    ],
    "ECMWF_AIFS": [
        {
            "latest": "20260601_00",
            "previous": "20260531_18",
            "file": "ECMWF_AIFS_shift_20260601_00_vs_20260531_18.gif"
        },
        {
            "latest": "20260601_00",
            "previous": "20260531_12",
            "file": "ECMWF_AIFS_shift_20260601_00_vs_20260531_12.gif"
        },
        {
            "latest": "20260531_12",
            "previous": "20260531_06",
            "file": "ECMWF_AIFS_shift_20260531_12_vs_20260531_06.gif"
        },
        {
            "latest": "20260531_12",
            "previous": "20260531_00",
            "file": "ECMWF_AIFS_shift_20260531_12_vs_20260531_00.gif"
        },
        {
            "latest": "20260531_06",
            "previous": "20260531_00",
            "file": "ECMWF_AIFS_shift_20260531_06_vs_20260531_00.gif"
        },
        {
            "latest": "20260531_06",
            "previous": "20260530_18",
            "file": "ECMWF_AIFS_shift_20260531_06_vs_20260530_18.gif"
        },
        {
            "latest": "20260530_18",
            "previous": "20260530_12",
            "file": "ECMWF_AIFS_shift_20260530_18_vs_20260530_12.gif"
        },
        {
            "latest": "20260530_18",
            "previous": "20260530_06",
            "file": "ECMWF_AIFS_shift_20260530_18_vs_20260530_06.gif"
        },
        {
            "latest": "20260530_12",
            "previous": "20260530_06",
            "file": "ECMWF_AIFS_shift_20260530_12_vs_20260530_06.gif"
        },
        {
            "latest": "20260530_12",
            "previous": "20260530_00",
            "file": "ECMWF_AIFS_shift_20260530_12_vs_20260530_00.gif"
        },
        {
            "latest": "20260530_06",
            "previous": "20260530_00",
            "file": "ECMWF_AIFS_shift_20260530_06_vs_20260530_00.gif"
        },
        {
            "latest": "20260530_06",
            "previous": "20260529_18",
            "file": "ECMWF_AIFS_shift_20260530_06_vs_20260529_18.gif"
        }
    ]
}